LICENSE
MANIFEST.in
README.md
setup.py
bin/withings
pywithings.egg-info/PKG-INFO
pywithings.egg-info/SOURCES.txt
pywithings.egg-info/dependency_links.txt
pywithings.egg-info/requires.txt
pywithings.egg-info/top_level.txt
pywithings.egg-info/zip-safe
requirements/base.txt
requirements/test.txt
withings/__init__.py